LICENSE
MANIFEST.in
README.md
pyproject.toml
src/wedme/__init__.py
src/wedme/const.py
src/wedme/gif.py
src/wedme/saving.py
src/wedme/shorthands.py
src/wedme/styledefs.py
src/wedme/util.py
src/wedme/apply/a0.py
src/wedme/apply/dev.py
src/wedme/apply/paper.py
src/wedme/apply/slides.py
src/wedme/apply/thesis.py
src/wedme/scale/__init__.py
src/wedme/scale/custom_func_scale.py
src/wedme/stylesheets/a0.mplstyle
src/wedme/stylesheets/common.mplstyle
src/wedme/stylesheets/elspaper.mplstyle
src/wedme/stylesheets/slides.mplstyle
src/wedme/stylesheets/thesis.mplstyle
src/wedme_plots.egg-info/PKG-INFO
src/wedme_plots.egg-info/SOURCES.txt
src/wedme_plots.egg-info/dependency_links.txt
src/wedme_plots.egg-info/requires.txt
src/wedme_plots.egg-info/top_level.txt