Metadata-Version: 2.1
Name: wedme-plots
Version: 2.0.4
Summary: We Don't Make Embarrassing Plots. Matplotlib styles for papers, posters, presentations and theses.
Author-email: Martijn Ruijzendaal <martijn.ruijzendaal@gmail.com>
License: MIT License
Project-URL: repository, https://github.com/mruijzendaal/wedme-plots
Project-URL: documentation, https://github.com/mruijzendaal/wedme-plots
Keywords: matplotlib
Classifier: License :: OSI Approved :: MIT License
Classifier: Programming Language :: Python
Classifier: Programming Language :: Python :: 3
Requires-Python: >=3.7
License-File: LICENSE
Requires-Dist: matplotlib
Requires-Dist: importlib_resources
Provides-Extra: build
Requires-Dist: build; extra == "build"
Requires-Dist: twine; extra == "build"
Provides-Extra: dev
Requires-Dist: black; extra == "dev"
Requires-Dist: pytest; extra == "dev"
